Workbook

Sheet Portfolio
A1: Asset_ID | B1: Asset_Type | C1: Name | D1: Ticker | E1: Yahoo_Ticker | F1: ISIN | G1: Quantity | H1: Purchase_Price | I1: Currency | J1: Purchase_FX_to_DKK | K1: Current_Price | L1: Current_FX_to_DKK | M1: Cost_Value_DKK | N1: Market_Value_DKK | O1: Local_Return_Pct | P1: FX_Return_Pct | Q1: Return_DKK | R1: Return_Pct | S1: Portfolio_Weight | T1: Sector | U1: Account | V1: Include_Analytics | W1: Include_Weight | X1: Price_Source | Y1: FX_Source | Z1: Last_Updated | AA1: Data_Quality_Flag | AB1: Notes
A2: A001 | B2: Stock | C2: ABB Ltd | D2: ABB:XSTO | E2: ABB.ST | G2: 22 | H2: 923.49 | I2: SEK | K2: 974 | L2: =IF(I2="DKK",1,IFERROR(_xludf.XLOOKUP(I2,FX!$A$2:$A$20,FX!$B$2:$B$20,""),"")) | M2: =IFERROR(G2*H2*J2,"") -> 0 | N2: =IFERROR(G2*K2*L2,"") | O2: =IFERROR(K2/H2-1,"") -> 0.054694691 | P2: =IFERROR(L2/J2-1,"") | Q2: =IFERROR(N2-M2,"") | R2: =IFERROR(N2/M2-1,"") | S2: =IF(W2=TRUE,IFERROR(N2/SUMIFS($N$2:$N$501,$W$2:$W$501,TRUE),0),0) -> 0 | T2: Infrastruktur | U2: ASK | V2: TRUE | W2: TRUE | X2: Manual/Market data | Y2: FX sheet
A3: A002 | B3: Stock | C3: AL Sydbank A/S | D3: ALSYDB:XCSE | E3: ALSYDB.CO | G3: 64 | H3: 493.03 | I3: DKK | J3: 1 | K3: 637.5 | L3: =IF(I3="DKK",1,IFERROR(_xludf.XLOOKUP(I3,FX!$A$2:$A$20,FX!$B$2:$B$20,""),"")) -> 1 | M3: =IFERROR(G3*H3*J3,"") -> 31553.92 | N3: =IFERROR(G3*K3*L3,"") -> 40800 | O3: =IFERROR(K3/H3-1,"") -> 0.29302477 | P3: =IFERROR(L3/J3-1,"") -> 0 | Q3: =IFERROR(N3-M3,"") -> 9246.08 | R3: =IFERROR(N3/M3-1,"") -> 0.29302477 | S3: =IF(W3=TRUE,IFERROR(N3/SUMIFS($N$2:$N$501,$W$2:$W$501,TRUE),0),0) -> 0.055005901 | T3: Finans | U3: ASK | V3: TRUE | W3: TRUE | X3: Manual/Market data | Y3: FX sheet
A4: A003 | B4: Stock | C4: Alphabet Inc. Class C | D4: GOOG:MIL | E4: GOOG:MIL | G4: 6 | H4: 254.9 | I4: EUR | K4: 253.95 | O4: =IFERROR(K4/H4-1,"") -> -0.0037269517 | T4: Teknologi | U4: ASK | V4: TRUE | W4: TRUE | X4: Manual/Market data | Y4: FX sheet
A5: A004 | B5: Stock | C5: ASML Holding NV | D5: ASML:XAMS | E5: ASML.AS | G5: 4 | H5: 1199.3 | I5: EUR | K5: 1497.8 | L5: =IF(I5="DKK",1,IFERROR(_xludf.XLOOKUP(I5,FX!$A$2:$A$20,FX!$B$2:$B$20,""),"")) | M5: =IFERROR(G5*H5*J5,"") -> 0 | N5: =IFERROR(G5*K5*L5,"") | O5: =IFERROR(K5/H5-1,"") -> 0.24889519 | P5: =IFERROR(L5/J5-1,"") | Q5: =IFERROR(N5-M5,"") | R5: =IFERROR(N5/M5-1,"") | S5: =IF(W5=TRUE,IFERROR(N5/SUMIFS($N$2:$N$501,$W$2:$W$501,TRUE),0),0) -> 0 | T5: Teknologi | U5: ASK | V5: TRUE | W5: TRUE | X5: Manual/Market data | Y5: FX sheet
A6: A005 | B6: Stock | C6: Celestica Inc. | D6: CLS:XNYS | E6: CLS | G6: 9 | H6: 292.97 | I6: USD | K6: 316.23 | O6: =IFERROR(K6/H6-1,"") -> 0.079393795 | P6: =IFERROR(L6/J6-1,"") | Q6: =IFERROR(N6-M6,"") -> 0 | R6: =IFERROR(N6/M6-1,"") | S6: =IF(W6=TRUE,IFERROR(N6/SUMIFS($N$2:$N$501,$W$2:$W$501,TRUE),0),0) -> 0 | T6: Teknologi | U6: ASK | V6: TRUE | W6: TRUE | X6: Manual/Market data | Y6: FX sheet
A7: A006 | B7: Stock | C7: Danske Bank A/S | D7: DANSKE:XCSE | E7: DANSKE.CO | G7: 125 | H7: 212.15 | I7: DKK | J7: 1 | K7: 377.4 | L7: =IF(I7="DKK",1,IFERROR(_xludf.XLOOKUP(I7,FX!$A$2:$A$20,FX!$B$2:$B$20,""),"")) -> 1 | M7: =IFERROR(G7*H7*J7,"") -> 26518.75 | N7: =IFERROR(G7*K7*L7,"") -> 47175 | O7: =IFERROR(K7/H7-1,"") -> 0.77893 | P7: =IFERROR(L7/J7-1,"") -> 0 | Q7: =IFERROR(N7-M7,"") -> 20656.25 | R7: =IFERROR(N7/M7-1,"") -> 0.77893 | S7: =IF(W7=TRUE,IFERROR(N7/SUMIFS($N$2:$N$501,$W$2:$W$501,TRUE),0),0) -> 0.063600573 | T7: Finans | U7: ASK | V7: TRUE | W7: TRUE | X7: Manual/Market data | Y7: FX sheet
A8: A007 | B8: Stock | C8: Frontline PLC | D8: FRO | E8: FRO | G8: 76 | H8: 47.25 | I8: USD | K8: 40 | L8: =IF(I8="DKK",1,IFERROR(_xludf.XLOOKUP(I8,FX!$A$2:$A$20,FX!$B$2:$B$20,""),"")) | M8: =IFERROR(G8*H8*J8,"") -> 0 | N8: =IFERROR(G8*K8*L8,"") | O8: =IFERROR(K8/H8-1,"") -> -0.15343915 | P8: =IFERROR(L8/J8-1,"") | Q8: =IFERROR(N8-M8,"") | R8: =IFERROR(N8/M8-1,"") | S8: =IF(W8=TRUE,IFERROR(N8/SUMIFS($N$2:$N$501,$W$2:$W$501,TRUE),0),0) -> 0 | T8: Industri | U8: ASK | V8: TRUE | W8: TRUE | X8: Manual/Market data | Y8: FX sheet
A9: A008 | B9: Stock | C9: MICROSOFT CORPORATION | D9: MSF:XETR | E9: MSF.DE | G9: 16 | H9: 394.77 | I9: EUR | K9: 425 | L9: =IF(I9="DKK",1,IFERROR(_xludf.XLOOKUP(I9,FX!$A$2:$A$20,FX!$B$2:$B$20,""),"")) | M9: =IFERROR(G9*H9*J9,"") -> 0 | N9: =IFERROR(G9*K9*L9,"") | O9: =IFERROR(K9/H9-1,"") -> 0.076576234 | P9: =IFERROR(L9/J9-1,"") | Q9: =IFERROR(N9-M9,"") | R9: =IFERROR(N9/M9-1,"") | S9: =IF(W9=TRUE,IFERROR(N9/SUMIFS($N$2:$N$501,$W$2:$W$501,TRUE),0),0) -> 0 | T9: Teknologi | U9: ASK | V9: TRUE | W9: TRUE | X9: Manual/Market data | Y9: FX sheet
A10: A009 | B10: Stock | C10: Nkt A/S | D10: NKT.CO | E10: NKT.CO | G10: 63 | H10: 405.68 | I10: DKK | J10: 1 | K10: 910 | L10: =IF(I10="DKK",1,IFERROR(_xludf.XLOOKUP(I10,FX!$A$2:$A$20,FX!$B$2:$B$20,""),"")) -> 1 | M10: =IFERROR(G10*H10*J10,"") -> 25557.84 | N10: =IFERROR(G10*K10*L10,"") -> 57330 | O10: =IFERROR(K10/H10-1,"") -> 1.2431473 | P10: =IFERROR(L10/J10-1,"") -> 0 | Q10: =IFERROR(N10-M10,"") -> 31772.16 | R10: =IFERROR(N10/M10-1,"") -> 1.2431473 | S10: =IF(W10=TRUE,IFERROR(N10/SUMIFS($N$2:$N$501,$W$2:$W$501,TRUE),0),0) -> 0.07729138 | T10: Industri | U10: ASK | V10: TRUE | W10: TRUE | X10: Manual/Market data | Y10: FX sheet
A11: A010 | B11: Stock | C11: Novo Nordisk A/S | D11: NOVO-B.CO | E11: NOVO-B.CO | G11: 396 | H11: 433 | I11: DKK | J11: 1 | K11: 298 | L11: =IF(I11="DKK",1,IFERROR(_xludf.XLOOKUP(I11,FX!$A$2:$A$20,FX!$B$2:$B$20,""),"")) -> 1 | M11: =IFERROR(G11*H11*J11,"") -> 171468 | N11: =IFERROR(G11*K11*L11,"") -> 118008 | O11: =IFERROR(K11/H11-1,"") -> -0.31177829 | P11: =IFERROR(L11/J11-1,"") -> 0 | Q11: =IFERROR(N11-M11,"") -> -53460 | R11: =IFERROR(N11/M11-1,"") -> -0.31177829 | S11: =IF(W11=TRUE,IFERROR(N11/SUMIFS($N$2:$N$501,$W$2:$W$501,TRUE),0),0) -> 0.15909648 | T11: Sundhed | U11: ASK | V11: TRUE | W11: TRUE | X11: Manual/Market data | Y11: FX sheet
A12: A011 | B12: Stock | C12: Pandora A/S | D12: PNDORA:XCSE | E12: PNDORA.CO | G12: 33 | H12: 710.62 | I12: DKK | J12: 1 | K12: 846.8 | L12: =IF(I12="DKK",1,IFERROR(_xludf.XLOOKUP(I12,FX!$A$2:$A$20,FX!$B$2:$B$20,""),"")) -> 1 | M12: =IFERROR(G12*H12*J12,"") -> 23450.46 | N12: =IFERROR(G12*K12*L12,"") -> 27944.4 | O12: =IFERROR(K12/H12-1,"") -> 0.19163547 | P12: =IFERROR(L12/J12-1,"") -> 0 | Q12: =IFERROR(N12-M12,"") -> 4493.94 | R12: =IFERROR(N12/M12-1,"") -> 0.19163547 | S12: =IF(W12=TRUE,IFERROR(N12/SUMIFS($N$2:$N$501,$W$2:$W$501,TRUE),0),0) -> 0.037674189 | T12: Forbrug | U12: ASK | V12: TRUE | W12: TRUE | X12: Manual/Market data | Y12: FX sheet
A13: A013 | B13: Stock | C13: Siemens Energy AG | D13: ENR:XETR | E13: ENR.DE | G13: 21 | H13: 137.86 | I13: EUR | K13: 157.72 | L13: =IF(I13="DKK",1,IFERROR(_xludf.XLOOKUP(I13,FX!$A$2:$A$20,FX!$B$2:$B$20,""),"")) | M13: =IFERROR(G13*H13*J13,"") -> 0 | N13: =IFERROR(G13*K13*L13,"") | O13: =IFERROR(K13/H13-1,"") -> 0.14405919 | P13: =IFERROR(L13/J13-1,"") | Q13: =IFERROR(N13-M13,"") | R13: =IFERROR(N13/M13-1,"") | S13: =IF(W13=TRUE,IFERROR(N13/SUMIFS($N$2:$N$501,$W$2:$W$501,TRUE),0),0) -> 0 | T13: Infrastruktur | U13: ASK | V13: TRUE | W13: TRUE | X13: Manual/Market data | Y13: FX sheet
A14: A014 | B14: Stock | C14: Taiwan Semiconductor Manufacturing Co. Ltd. | D14: TSM:XNYS | E14: TSM | G14: 8 | H14: 408.97 | I14: USD | K14: 418 | L14: =IF(I14="DKK",1,IFERROR(_xludf.XLOOKUP(I14,FX!$A$2:$A$20,FX!$B$2:$B$20,""),"")) | M14: =IFERROR(G14*H14*J14,"") -> 0 | N14: =IFERROR(G14*K14*L14,"") | O14: =IFERROR(K14/H14-1,"") -> 0.022079859 | P14: =IFERROR(L14/J14-1,"") | Q14: =IFERROR(N14-M14,"") | R14: =IFERROR(N14/M14-1,"") | S14: =IF(W14=TRUE,IFERROR(N14/SUMIFS($N$2:$N$501,$W$2:$W$501,TRUE),0),0) -> 0 | T14: Teknologi | U14: ASK | V14: TRUE | W14: TRUE | X14: Manual/Market data | Y14: FX sheet
A15: A015 | B15: Stock | C15: Vestas Wind System | D15: VWS:XCSE | E15: VWS.CO | G15: 104 | H15: 155.74 | I15: DKK | J15: 1 | K15: 176.55 | L15: =IF(I15="DKK",1,IFERROR(_xludf.XLOOKUP(I15,FX!$A$2:$A$20,FX!$B$2:$B$20,""),"")) -> 1 | M15: =IFERROR(G15*H15*J15,"") -> 16196.96 | N15: =IFERROR(G15*K15*L15,"") -> 18361.2 | O15: =IFERROR(K15/H15-1,"") -> 0.13362014 | P15: =IFERROR(L15/J15-1,"") -> 0 | Q15: =IFERROR(N15-M15,"") -> 2164.24 | R15: =IFERROR(N15/M15-1,"") -> 0.13362014 | S15: =IF(W15=TRUE,IFERROR(N15/SUMIFS($N$2:$N$501,$W$2:$W$501,TRUE),0),0) -> 0.024754273 | T15: Vedvarende energi | U15: ASK | V15: TRUE | W15: TRUE | X15: Manual/Market data | Y15: FX sheet
A16: A016 | B16: ETF | C16: Global X Copper Miners UCITS ETF | D16: 4COP.DE | E16: 4COP.DE | G16: 12 | H16: 60.59 | I16: USD | K16: 58 | L16: =IF(I16="DKK",1,IFERROR(_xludf.XLOOKUP(I16,FX!$A$2:$A$20,FX!$B$2:$B$20,""),"")) | M16: =IFERROR(G16*H16*J16,"") -> 0 | N16: =IFERROR(G16*K16*L16,"") | O16: =IFERROR(K16/H16-1,"") -> -0.042746328 | P16: =IFERROR(L16/J16-1,"") | Q16: =IFERROR(N16-M16,"") | R16: =IFERROR(N16/M16-1,"") | S16: =IF(W16=TRUE,IFERROR(N16/SUMIFS($N$2:$N$501,$W$2:$W$501,TRUE),0),0) -> 0 | T16: Materialer | U16: ASK | V16: TRUE | W16: TRUE | X16: Manual/Market data | Y16: FX sheet | AA16: VERIFY_CURRENCY
A17: A017 | B17: ETF | C17: Global X U.S Infrastructure Development UCITS ETF | D17: 94VE.DE | E17: 94VE.DE | G17: 39 | H17: 46.039 | I17: EUR | K17: 48 | L17: =IF(I17="DKK",1,IFERROR(_xludf.XLOOKUP(I17,FX!$A$2:$A$20,FX!$B$2:$B$20,""),"")) | M17: =IFERROR(G17*H17*J17,"") -> 0 | N17: =IFERROR(G17*K17*L17,"") | O17: =IFERROR(K17/H17-1,"") -> 0.042594322 | P17: =IFERROR(L17/J17-1,"") | Q17: =IFERROR(N17-M17,"") | R17: =IFERROR(N17/M17-1,"") | S17: =IF(W17=TRUE,IFERROR(N17/SUMIFS($N$2:$N$501,$W$2:$W$501,TRUE),0),0) -> 0 | T17: Infrastruktur | U17: ASK | V17: TRUE | W17: TRUE | X17: Manual/Market data | Y17: FX sheet
A18: A018 | B18: ETF | C18: Global X Uranium UCITS ETF | D18: URNU.DE | E18: URNU.DE | G18: 52 | H18: 28.96 | I18: EUR | K18: 23 | L18: =IF(I18="DKK",1,IFERROR(_xludf.XLOOKUP(I18,FX!$A$2:$A$20,FX!$B$2:$B$20,""),"")) | M18: =IFERROR(G18*H18*J18,"") -> 0 | N18: =IFERROR(G18*K18*L18,"") | O18: =IFERROR(K18/H18-1,"") -> -0.2058011 | P18: =IFERROR(L18/J18-1,"") | Q18: =IFERROR(N18-M18,"") | R18: =IFERROR(N18/M18-1,"") | S18: =IF(W18=TRUE,IFERROR(N18/SUMIFS($N$2:$N$501,$W$2:$W$501,TRUE),0),0) -> 0 | T18: Vedvarende energi | U18: ASK | V18: TRUE | W18: TRUE | X18: Manual/Market data | Y18: FX sheet
A19: A019 | B19: ETF | C19: iShares Edge MSCI World Quality Factor UCITS ETF | D19: IS3Q:XETR | E19: IS3Q.DE | G19: 50 | H19: 80.14 | I19: EUR | K19: 79 | O19: =IFERROR(K19/H19-1,"") -> -0.014225106 | T19: World | U19: ASK | V19: TRUE | W19: TRUE | X19: Manual/Market data | Y19: FX sheet
A20: A020 | B20: ETF | C20: iShs Global Clean Energy ETF | D20: IQQH.DE | E20: IQQH.DE | G20: 185 | H20: 10.62 | I20: EUR | K20: 9.3 | L20: =IF(I20="DKK",1,IFERROR(_xludf.XLOOKUP(I20,FX!$A$2:$A$20,FX!$B$2:$B$20,""),"")) | M20: =IFERROR(G20*H20*J20,"") -> 0 | N20: =IFERROR(G20*K20*L20,"") | O20: =IFERROR(K20/H20-1,"") -> -0.12429379 | P20: =IFERROR(L20/J20-1,"") | Q20: =IFERROR(N20-M20,"") | R20: =IFERROR(N20/M20-1,"") | S20: =IF(W20=TRUE,IFERROR(N20/SUMIFS($N$2:$N$501,$W$2:$W$501,TRUE),0),0) -> 0 | T20: Vedvarende energi | U20: ASK | V20: TRUE | W20: TRUE | X20: Manual/Market data | Y20: FX sheet
A21: A021 | B21: ETF | C21: iShs MSCI Global Semiconductors UCITS ETF | D21: SEC0.DE | E21: SEC0.DE | G21: 313 | H21: 10.427 | I21: EUR | K21: 17 | L21: =IF(I21="DKK",1,IFERROR(_xludf.XLOOKUP(I21,FX!$A$2:$A$20,FX!$B$2:$B$20,""),"")) | M21: =IFERROR(G21*H21*J21,"") -> 0 | N21: =IFERROR(G21*K21*L21,"") | O21: =IFERROR(K21/H21-1,"") -> 0.63038266 | P21: =IFERROR(L21/J21-1,"") | Q21: =IFERROR(N21-M21,"") | R21: =IFERROR(N21/M21-1,"") | S21: =IF(W21=TRUE,IFERROR(N21/SUMIFS($N$2:$N$501,$W$2:$W$501,TRUE),0),0) -> 0 | T21: Teknologi | U21: ASK | V21: TRUE | W21: TRUE | X21: Manual/Market data | Y21: FX sheet
A22: A022 | B22: ETF | C22: iShares NASDAQ US Biotechnology UCITS ETF | D22: 2B70.DE | E22: 2B70.DE | G22: 262 | H22: 8.89 | I22: EUR | K22: 8 | L22: =IF(I22="DKK",1,IFERROR(_xludf.XLOOKUP(I22,FX!$A$2:$A$20,FX!$B$2:$B$20,""),"")) | M22: =IFERROR(G22*H22*J22,"") -> 0 | N22: =IFERROR(G22*K22*L22,"") | O22: =IFERROR(K22/H22-1,"") -> -0.10011249 | P22: =IFERROR(L22/J22-1,"") | Q22: =IFERROR(N22-M22,"") | R22: =IFERROR(N22/M22-1,"") | S22: =IF(W22=TRUE,IFERROR(N22/SUMIFS($N$2:$N$501,$W$2:$W$501,TRUE),0),0) -> 0 | T22: Bioteknologi | U22: ASK | V22: TRUE | W22: TRUE | X22: Manual/Market data | Y22: FX sheet
A23: A023 | B23: ETF | C23: VanEck Defense UCITS ETF | D23: DFEN.DE | E23: DFEN.DE | G23: 44 | H23: 56.9 | I23: EUR | K23: 56 | L23: =IF(I23="DKK",1,IFERROR(_xludf.XLOOKUP(I23,FX!$A$2:$A$20,FX!$B$2:$B$20,""),"")) | M23: =IFERROR(G23*H23*J23,"") -> 0 | N23: =IFERROR(G23*K23*L23,"") | O23: =IFERROR(K23/H23-1,"") -> -0.015817223 | P23: =IFERROR(L23/J23-1,"") | Q23: =IFERROR(N23-M23,"") | R23: =IFERROR(N23/M23-1,"") | S23: =IF(W23=TRUE,IFERROR(N23/SUMIFS($N$2:$N$501,$W$2:$W$501,TRUE),0),0) -> 0 | T23: Forsvar | U23: ASK | V23: TRUE | W23: TRUE | X23: Manual/Market data | Y23: FX sheet
A24: A024 | B24: ETF | C24: VanEck Quantum Computing UCITS ETF | D24: QUTM.DE | E24: QUTM.DE | G24: 30 | H24: 27.025 | I24: EUR | K24: 26 | L24: =IF(I24="DKK",1,IFERROR(_xludf.XLOOKUP(I24,FX!$A$2:$A$20,FX!$B$2:$B$20,""),"")) | M24: =IFERROR(G24*H24*J24,"") -> 0 | N24: =IFERROR(G24*K24*L24,"") | O24: =IFERROR(K24/H24-1,"") -> -0.037927845 | P24: =IFERROR(L24/J24-1,"") | Q24: =IFERROR(N24-M24,"") | R24: =IFERROR(N24/M24-1,"") | S24: =IF(W24=TRUE,IFERROR(N24/SUMIFS($N$2:$N$501,$W$2:$W$501,TRUE),0),0) -> 0 | T24: Teknologi | U24: ASK | V24: TRUE | W24: TRUE | X24: Manual/Market data | Y24: FX sheet
A25: A025 | B25: ETF | C25: VanEck Rare Earth and Strategic Metals UCITS ETF | D25: VVMX.DE | E25: VVMX.DE | G25: 161 | H25: 16.59 | I25: EUR | K25: 12 | L25: =IF(I25="DKK",1,IFERROR(_xludf.XLOOKUP(I25,FX!$A$2:$A$20,FX!$B$2:$B$20,""),"")) | M25: =IFERROR(G25*H25*J25,"") -> 0 | N25: =IFERROR(G25*K25*L25,"") | O25: =IFERROR(K25/H25-1,"") -> -0.27667269 | P25: =IFERROR(L25/J25-1,"") | Q25: =IFERROR(N25-M25,"") | R25: =IFERROR(N25/M25-1,"") | S25: =IF(W25=TRUE,IFERROR(N25/SUMIFS($N$2:$N$501,$W$2:$W$501,TRUE),0),0) -> 0 | T25: Materialer | U25: ASK | V25: TRUE | W25: TRUE | X25: Manual/Market data | Y25: FX sheet
A26: A026 | B26: ETF | C26: VanEck S&P Global Mining UCITS ETF | D26: WMIN.DE | E26: WMIN.DE | G26: 16 | H26: 58.1 | I26: EUR | K26: 54 | L26: =IF(I26="DKK",1,IFERROR(_xludf.XLOOKUP(I26,FX!$A$2:$A$20,FX!$B$2:$B$20,""),"")) | M26: =IFERROR(G26*H26*J26,"") -> 0 | N26: =IFERROR(G26*K26*L26,"") | O26: =IFERROR(K26/H26-1,"") -> -0.070567986 | P26: =IFERROR(L26/J26-1,"") | Q26: =IFERROR(N26-M26,"") | R26: =IFERROR(N26/M26-1,"") | S26: =IF(W26=TRUE,IFERROR(N26/SUMIFS($N$2:$N$501,$W$2:$W$501,TRUE),0),0) -> 0 | T26: Materialer | U26: ASK | V26: TRUE | W26: TRUE | X26: Manual/Market data | Y26: FX sheet
A27: A027 | B27: ETF | C27: VanEck Space Innovators UCITS ETF | D27: JEDI.DE | E27: JEDI.DE | G27: 15 | H27: 95.08 | I27: EUR | K27: 75 | L27: =IF(I27="DKK",1,IFERROR(_xludf.XLOOKUP(I27,FX!$A$2:$A$20,FX!$B$2:$B$20,""),"")) | M27: =IFERROR(G27*H27*J27,"") -> 0 | N27: =IFERROR(G27*K27*L27,"") | O27: =IFERROR(K27/H27-1,"") -> -0.21119058 | P27: =IFERROR(L27/J27-1,"") | Q27: =IFERROR(N27-M27,"") | R27: =IFERROR(N27/M27-1,"") | S27: =IF(W27=TRUE,IFERROR(N27/SUMIFS($N$2:$N$501,$W$2:$W$501,TRUE),0),0) -> 0 | T27: Space | U27: ASK | V27: TRUE | W27: TRUE | X27: Manual/Market data | Y27: FX sheet
A28: A028 | B28: ETF | C28: Vanguard FTSE All-World UCITS Acc ETF | D28: VWCE.DE | E28: VWCE.DE | G28: 38 | H28: 166.35 | I28: EUR | K28: 175.52 | L28: =IF(I28="DKK",1,IFERROR(_xludf.XLOOKUP(I28,FX!$A$2:$A$20,FX!$B$2:$B$20,""),"")) | M28: =IFERROR(G28*H28*J28,"") -> 0 | N28: =IFERROR(G28*K28*L28,"") | O28: =IFERROR(K28/H28-1,"") -> 0.055124737 | P28: =IFERROR(L28/J28-1,"") | Q28: =IFERROR(N28-M28,"") | R28: =IFERROR(N28/M28-1,"") | S28: =IF(W28=TRUE,IFERROR(N28/SUMIFS($N$2:$N$501,$W$2:$W$501,TRUE),0),0) -> 0 | T28: World | U28: Pension | V28: TRUE | W28: TRUE | X28: Manual/Market data | Y28: FX sheet
A29: A029 | B29: ETF | C29: Vanguard FTSE All-World High Dvd Yield UCITS ETF | D29: VGWD.DE | E29: VGWD.DE | G29: 17 | H29: 80.75 | I29: EUR | K29: 80.75 | M29: =IFERROR(G29*H29*J29,"") -> 0 | O29: =IFERROR(K29/H29-1,"") -> 0 | S29: =IF(W29=TRUE,IFERROR(N29/SUMIFS($N$2:$N$501,$W$2:$W$501,TRUE),0),0) -> 0 | T29: World | U29: Pension | V29: TRUE | W29: TRUE | X29: Manual/Market data | Y29: FX sheet
A30: A030 | B30: Stock | C30: Grundfos | D30: Grundfos | E30: Grundfos | G30: =260 -> 260 | H30: 637 | I30: DKK | J30: 1 | K30: 1662 | L30: =IF(I30="DKK",1,IFERROR(_xludf.XLOOKUP(I30,FX!$A$2:$A$20,FX!$B$2:$B$20,""),"")) -> 1 | M30: =IFERROR(G30*H30*J30,"") -> 165620 | N30: =IFERROR(G30*K30*L30,"") -> 432120 | O30: =IFERROR(K30/H30-1,"") -> 1.6091052 | P30: =IFERROR(L30/J30-1,"") -> 0 | Q30: =IFERROR(N30-M30,"") -> 266500 | R30: =IFERROR(N30/M30-1,"") -> 1.6091052 | S30: =IF(W30=TRUE,IFERROR(N30/SUMIFS($N$2:$N$501,$W$2:$W$501,TRUE),0),0) -> 0.5825772 | T30: Industri | U30: Depot | V30: FALSE | W30: TRUE | X30: Manual/Market data | Y30: FX sheet

Sheet Accounts
A1: Account | B1: Account_Type | C1: Tax_Type | D1: Include_Total | E1: Include_Active_Portfolio | F1: Notes
A2: ASK | B2: Investering | C2: ASK | D2: TRUE | E2: TRUE
A3: Pension | B3: Pension | C3: Pension | D3: TRUE | E3: TRUE
A4: Depot | B4: Unoteret/Depot | C4: Aktie | D4: TRUE | E4: FALSE | F4: Grundfos er uden for aktiv vægt

Sheet Settings
A1: Setting | B1: Value | C1: Unit | D1: Description
A2: Benchmark | B2: URTH | D2: Fælles benchmark
A3: Risk_Free_Rate | B3: 0.02 | C3: pct | D3: Til Sharpe/Sortino
A4: Max_Position_Weight | B4: 0.14 | C4: pct | D4: Maksimal vægt pr. position
A5: Momentum_1W | B5: 0.25 | C5: pct | D5: Momentumvægt
A6: Momentum_1M | B6: 0.25 | C6: pct | D6: Momentumvægt
A7: Momentum_3M | B7: 0.2 | C7: pct | D7: Momentumvægt
A8: Momentum_6M | B8: 0.2 | C8: pct | D8: Momentumvægt
A9: Momentum_12M | B9: 0.1 | C9: pct | D9: Momentumvægt
A10: Negative_Table_Text | B10: #FF4B4B | D10: Rød skrift for negative værdier
A11: Morning_Brief_Max_Actions | B11: 5 | C11: count | D11: Maksimalt antal handlinger på overblik

Sheet FX
A1: Currency | B1: Current_FX_to_DKK | C1: Rate_Date | D1: Source | E1: Manual_Fallback | F1: Use_Manual | G1: Data_Quality
A2: DKK | B2: 1 | D2: Fixed | E2: 1 | F2: FALSE | G2: OK
A3: EUR | D3: ECB/Yahoo | F3: FALSE | G3: MISSING
A4: USD | D4: ECB/Yahoo | F4: FALSE | G4: MISSING
A5: SEK | D5: ECB/Yahoo | F5: FALSE | G5: MISSING
A6: NOK | D6: ECB/Yahoo | F6: FALSE | G6: MISSING
A7: GBP | D7: ECB/Yahoo | F7: FALSE | G7: MISSING
A8: CHF | D8: ECB/Yahoo | F8: FALSE | G8: MISSING
A9: JPY | D9: ECB/Yahoo | F9: FALSE | G9: MISSING

Sheet Ticker_Map
A1: Ticker | B1: Yahoo_Ticker | C1: Exchange | D1: Currency | E1: Data_Source | F1: Verification_Status
A2: ABB:XSTO | B2: ABB.ST | C2: XSTO | D2: SEK | E2: Yahoo Finance | F2: OK
A3: ALSYDB:XCSE | B3: ALSYDB.CO | C3: XCSE | D3: DKK | E3: Yahoo Finance | F3: OK
A4: ASML:XAMS | B4: ASML.AS | C4: XAMS | D4: EUR | E4: Yahoo Finance | F4: OK
A5: GOOG:MIL | B5: GOOG | C5: MIL | D5: EUR | E5: Yahoo Finance | F5: OK
A6: CLS:XNYS | B6: CLS | C6: XNYS | D6: USD | E6: Yahoo Finance | F6: OK
A7: DANSKE:XCSE | B7: DANSKE.CO | C7: XCSE | D7: DKK | E7: Yahoo Finance | F7: OK
A8: FRO | B8: FRO | D8: USD | E8: Yahoo Finance | F8: OK
A9: MSF:XETR | B9: MSF.DE | C9: XETR | D9: EUR | E9: Yahoo Finance | F9: OK
A10: NKT.CO | B10: NKT.CO | D10: DKK | E10: Yahoo Finance | F10: OK
A11: NOVO-B.CO | B11: NOVO-B.CO | D11: DKK | E11: Yahoo Finance | F11: OK
A12: PNDORA:XCSE | B12: PNDORA.CO | C12: XCSE | D12: DKK | E12: Yahoo Finance | F12: OK
A13: 4S0:XETR | B13: 4S0.DE | C13: XETR | D13: EUR | E13: Yahoo Finance | F13: OK
A14: ENR:XETR | B14: ENR.DE | C14: XETR | D14: EUR | E14: Yahoo Finance | F14: OK
A15: TSM:XNYS | B15: TSM | C15: XNYS | D15: USD | E15: Yahoo Finance | F15: OK
A16: UNH:XETR | B16: UNH.DE | C16: XETR | D16: EUR | E16: Yahoo Finance | F16: OK
A17: VWS:XCSE | B17: VWS.CO | C17: XCSE | D17: DKK | E17: Yahoo Finance | F17: OK
A18: 4COP.DE | B18: 4COP.DE | C18: XETR | D18: EUR | E18: Yahoo Finance | F18: OK
A19: 94VE.DE | B19: 94VE.DE | D19: EUR | E19: Yahoo Finance | F19: OK
A20: IS3Q:XETR | B20: IS3Q.DE | D20: EUR | E20: Yahoo Finance | F20: OK
A21: IQQH.DE | B21: IQQH.DE | D21: EUR | E21: Yahoo Finance | F21: OK
A22: URNU.DE | B22: URNU.DE | D22: EUR | E22: Yahoo Finance | F22: OK
A23: SEC0.DE | B23: SEC0.DE | D23: EUR | E23: Yahoo Finance | F23: OK
A24: 2B70.DE | B24: 2B70.DE | D24: EUR | E24: Yahoo Finance | F24: OK
A25: DFEN.DE | B25: DFEN.DE | D25: EUR | E25: Yahoo Finance | F25: OK
A26: QUTM.DE | B26: QUTM.DE | D26: EUR | E26: Yahoo Finance | F26: OK
A27: VVMX.DE | B27: VVMX.DE | D27: EUR | E27: Yahoo Finance | F27: OK
A28: WMIN.DE | B28: WMIN.DE | D28: EUR | E28: Yahoo Finance | F28: OK
A29: JEDI.DE | B29: JEDI.DE | D29: EUR | E29: Yahoo Finance | F29: OK
A30: VWCE.DE | B30: VWCE.DE | D30: EUR | E30: Yahoo Finance | F30: OK
... A32: Grundfos | B32: Grundfos | D32: DKK | E32: Yahoo Finance | F32: OK

Sheet Watchlist
A1: Name | B1: Ticker | C1: Yahoo_Ticker | D1: Currency | E1: Sector | F1: Status | G1: Target_Buy | H1: Max_Price | I1: AI_Confidence | J1: Notes
A2: Astera Labs | B2: ALAB | C2: 64B.DE | D2: EUR | E2: Teknologi | I2: 94 | J2: Part of SEC0 0,49%

Sheet Cash
A1: Account | B1: Currency | C1: Amount | D1: FX_to_DKK | E1: Amount_DKK | F1: Include_Total | G1: Include_Active_Portfolio
A2: ASK | B2: DKK | C2: 121657 | D2: 1 | E2: =C2*D2 -> 121657 | F2: TRUE | G2: TRUE
